LICENSE
MANIFEST.in
README.md
setup.py
testflows.asyncio.egg-info/PKG-INFO
testflows.asyncio.egg-info/SOURCES.txt
testflows.asyncio.egg-info/dependency_links.txt
testflows.asyncio.egg-info/not-zip-safe
testflows.asyncio.egg-info/top_level.txt
testflows/asyncio/__init__.py
testflows/asyncio/asyncio.py