Metadata-Version: 2.1
Name: testflows.asyncio
Version: 1.1.210505.1133510
Summary: TestFlows - AsyncIO
Home-page: https://github.com/testflows/testflows-asyncio
Author: Vitaliy Zakaznikov
Author-email: vzakaznikov@testflows.com
License: Apache-2.0
Platform: UNKNOWN
Classifier: Development Status :: 2 - Pre-Alpha
Classifier: Programming Language :: Python :: 3
Classifier: License :: OSI Approved :: Apache Software License
Classifier: Operating System :: POSIX :: Linux
Requires-Python: >=3.6
